banknatchapolfunctions/__init__.py
banknatchapolfunctions/calculator.py
banknatchapolfunctions/eda.py
banknatchapolfunctions-0.2.0.dist-info/LICENCE.txt
banknatchapolfunctions-0.2.0.dist-info/METADATA
banknatchapolfunctions-0.2.0.dist-info/WHEEL
banknatchapolfunctions-0.2.0.dist-info/top_level.txt
banknatchapolfunctions-0.2.0.dist-info/RECORD
