Metadata-Version: 2.1
Name: banknatchapolfunctions
Version: 0.2.0
Summary: ฟังก์ชันของ Bank Natchapol
Home-page: 
Author: Bank Natchapol
Author-email: natchapol.pat@gmail.com
License: MIT
Keywords: banknatchapol
Classifier: Development Status :: 5 - Production/Stable
Classifier: Intended Audience :: Education
Classifier: Operating System :: Microsoft :: Windows :: Windows 11
Classifier: License :: OSI Approved :: MIT License
Classifier: Programming Language :: Python :: 3
License-File: LICENCE.txt
Requires-Dist: numpy
Requires-Dist: pandas
Requires-Dist: matplotlib
